standardbots/__init__.py
standardbots/auto_generated/__init__.py
standardbots/auto_generated/apis.py
standardbots/auto_generated/models.py
tests/fixtures/__init__.py
tests/fixtures/client_fixt.py
tests/fixtures/robot_fixt.py
tests/fixtures/routines_fixt.py
standardbots-2.20251208.25.dist-info/METADATA
standardbots-2.20251208.25.dist-info/WHEEL
standardbots-2.20251208.25.dist-info/top_level.txt
standardbots-2.20251208.25.dist-info/RECORD
