Metadata-Version: 2.4
Name: standardbots
Version: 2.20251208.25
Summary: Standard Bots RO1 Robotics API
Home-page: 
Author: Standard Bots Support
Author-email: support@standardbots.com
Keywords: Standard Bots RO1 Robotics API
Requires-Python: >=3.7
Requires-Dist: setuptools>=21.0.0
Requires-Dist: typing_extensions>=4.3.0
Requires-Dist: urllib3>=1.26.7
Dynamic: author
Dynamic: author-email
Dynamic: description
Dynamic: keywords
Dynamic: requires-dist
Dynamic: requires-python
Dynamic: summary
